LICENSE
README.md
setup.py
aerfrax/__init__.py
aerfrax/main.py
aerfrax.egg-info/PKG-INFO
aerfrax.egg-info/SOURCES.txt
aerfrax.egg-info/dependency_links.txt
aerfrax.egg-info/top_level.txt