Metadata-Version: 2.1
Name: aerfrax
Version: 0.0.1
Summary: A data serialization library.
Home-page: https://github.com/Aermoss/AerFrax
Author: Yusuf Rencber
Author-email: yusufrencber546@gmail.com
License: MIT
Platform: UNKNOWN
License-File: LICENSE
